aiosyncapi/__init__.py
aiosyncapi/exceptions.py
aiosyncapi/models.py
aiosyncapi/ponicode/__init__.py
aiosyncapi/ponicode/main_test.py
aiosyncapi/utils.py
aiosyncapi-0.0.6.dist-info/WHEEL
aiosyncapi-0.0.6.dist-info/METADATA
aiosyncapi-0.0.6.dist-info/RECORD
